LICENSE
MANIFEST.in
README.md
setup.py
arlpy/__init__.py
arlpy/bf.py
arlpy/comms.py
arlpy/dtla.py
arlpy/geo.py
arlpy/hidaq.py
arlpy/plot.py
arlpy/romanis.py
arlpy/signal.py
arlpy/stable.py
arlpy/unet.py
arlpy/utils.py
arlpy/uwa.py
arlpy/uwapm.py
arlpy.egg-info/PKG-INFO
arlpy.egg-info/SOURCES.txt
arlpy.egg-info/dependency_links.txt
arlpy.egg-info/requires.txt
arlpy.egg-info/top_level.txt