Metadata-Version: 2.1
Name: arlpy
Version: 1.9.0
Summary: ARL Python Tools
Home-page: https://github.com/org-arl/arlpy
Author: Mandar Chitre
Author-email: mandar@nus.edu.sg
License: BSD (3-clause)
Keywords: underwater acoustics signal processing communication
Platform: UNKNOWN
License-File: LICENSE
